ruthon/__init__.py
ruthon/examples.py
ruthon-0.1.0.dist-info/WHEEL
ruthon-0.1.0.dist-info/METADATA
ruthon-0.1.0.dist-info/RECORD
